cchat.py
cchat-0.1.0.dist-info/entry_points.txt
cchat-0.1.0.dist-info/licenses/LICENSE
cchat-0.1.0.dist-info/WHEEL
cchat-0.1.0.dist-info/METADATA
cchat-0.1.0.dist-info/RECORD
