Metadata-Version: 2.4
Name: cchat
Version: 0.1.0
Summary: Browse and search Claude Code conversation history from the terminal.
Author: asparagusbeef
Requires-Python: >=3.8
Classifier: Development Status :: 4 - Beta
Classifier: Environment :: Console
Classifier: Intended Audience :: Developers
Classifier: License :: OSI Approved :: MIT License
Classifier: Programming Language :: Python :: 3
Classifier: Topic :: Software Development
License-File: LICENSE
Project-URL: Homepage, https://github.com/asparagusbeef/cchat
Project-URL: Issues, https://github.com/asparagusbeef/cchat/issues
